cipherlib/__init__.py
cipherlib/analysis.py
cipherlib/bigrams.py
cipherlib/download.py
cipherlib/encryption.py
cipherlib/utils.py
cipherlibunicorn-0.1.1.dist-info/METADATA
cipherlibunicorn-0.1.1.dist-info/WHEEL
cipherlibunicorn-0.1.1.dist-info/top_level.txt
cipherlibunicorn-0.1.1.dist-info/RECORD
