Metadata-Version: 2.4
Name: cipherlibUnicorn
Version: 0.1.1
Summary: A Python library for substitution cipher encryption, decryption, and cryptanalysis
Author-email: Libor <7slzi5em@4wrd.cc>
License-Expression: MIT
Requires-Python: >=3.8
Requires-Dist: numpy
Requires-Dist: pandas
Requires-Dist: matplotlib
Requires-Dist: requests
Requires-Dist: beautifulsoup4
